{
    "header": {
        "regtype": {
            "pos": [1, 1],
            "pic": "9(01)"
        },
        "retcode": {
            "pos": [2, 2],
            "pic": "9(01)"
        },
        "retlit": {
            "pos": [3, 9],
            "pic": "X(07)"
        },
        "servcode": {
            "pos": [10, 11],
            "pic": "9(02)"
        },
        "servlit": {
            "pos": [12, 19],
            "pic": "X(08)"
        },
        "s1": {
            "pos": [20, 26],
            "pic": "X(07)"
        },
        "branch": {
            "pos": [27, 30],
            "pic": "9(04)"
        },
        "branchdv": {
            "pos": [31, 31],
            "pic": "X(01)"
        },
        "account": {
            "pos": [32, 39],
            "pic": "9(08)"
        },
        "accountdv": {
            "pos": [40, 40],
            "pic": "X(01)"
        },
        "z1": {
            "pos": [41, 46],
            "pic": "9(06)"
        },
        "companyname": {
            "pos": [47, 76],
            "pic": "X(30)"
        },
        "bankname": {
            "pos": [77, 94],
            "pic": "X(18)"
        },
        "gendate": {
            "pos": [95, 100],
            "pic": "9(06)",
            "type": "date",
            "def": "@auto"
        },
        "seqrem": {
            "pos": [101, 107],
            "pic": "9(7)"
        },
        "s2": {
            "pos": [108, 129],
            "pic": "X(22)"
        },
        "convnum": {
            "pos": [130, 136],
            "pic": "9(7)"
        },
        "s3": {
            "pos": [137, 394],
            "pic": "X(258)"
        },
        "seq": {
            "pos": [395, 400],
            "pic": "9(06)"
        }
    },
    "detail": {
        "regtype": {
            "pos": [1, 1],
            "pic": "9(01)"
        },
        "z1": {
            "pos": [2, 3],
            "pic": "9(02)"
        },
        "z2": {
            "pos": [4, 17],
            "pic": "9(14)"
        },
        "branch": {
            "pos": [18, 21],
            "pic": "9(04)"
        },
        "branchdv": {
            "pos": [22, 22],
            "pic": "X(01)"
        },
        "account": {
            "pos": [24, 30],
            "pic": "9(08)"
        },
        "accountdv": {
            "pos": [31, 31],
            "pic": "X(01)"
        },
        "convum": {
            "pos": [32, 38],
            "pic": "9(07)"
        },
        "companyuse": {
            "pos": [39, 63],
            "pic": "X(25)"
        },
        "ournumber": {
            "pos": [64, 80],
            "pic": "9(17)"
        },
        "typebilling": {
            "pos": [81, 81],
            "pic": "9(01)"
        },
        "typebillingcommand72": {
            "pos": [82, 82],
            "pic": "9(01)"
        },
        "daycalc": {
            "pos": [83, 86],
            "pic": "9(04)"
        },
        "occurrcode": {
            "pos": [87, 88],
            "pic": "9(01)"
        },
        "s2": {
            "pos": [89, 91],
            "pic": "X(03)"
        },
        "portfoliovar": {
            "pos": [92, 94],
            "pic": "9(03)"
        },
        "escrowaccount": {
            "pos": [95, 95],
            "pic": "9(01)"
        },
        "discounttx": {
            "pos": [96, 100],
            "pic": "9(05)"
        },
        "ioftx": {
            "pos": [101, 105],
            "pic": "9(05)"
        },
        "s3": {
            "pos": [106, 106],
            "pic": "9(01)"
        },
        "portfolio": {
            "pos": [107, 108],
            "pic": "9(01)"
        },
        "command": {
            "pos": [109, 110],
            "pic": "9(02)"
        },
        "saleoffdate": {
            "pos": [111, 116],
            "pic": "9(06)",
            "type": "date"
        },
        "title": {
            "pos": [117, 126],
            "pic": "X(10)"
        },
        "s4": {
            "pos": [127, 146],
            "pic": "X(20)"
        },
        "expiration": {
            "pos": [147, 152],
            "pic": "9(6)",
            "type": "date"
        },
        "value": {
            "pos": [153, 165],
            "pic": "9(11)V9(2)"
        },
        "recbankcode": {
            "pos": [166, 168],
            "pic": "9(03)"
        },
        "recbranch": {
            "pos": [169, 172],
            "pic": "9(04)"
        },
        "recbranchddv": {
            "pos": [173, 173],
            "pic": "9(01)"
        },
        "especies": {
            "pos": [174, 175],
            "pic": "9(02)"
        },
        "creditdate": {
            "pos": [176, 181],
            "pic": "9(6)",
            "type": "date"
        },
        "billingfare": {
            "pos": [182, 188],
            "pic": "9(11)V9(2)"
        },
        "otherexpens": {
            "pos": [189, 201],
            "pic": "9(11)V9(2)"
        },
        "interestdiscount": {
            "pos": [202, 214],
            "pic": "9(11)V9(2)"
        },
        "discountiof": {
            "pos": [215, 227],
            "pic": "9(11)V9(2)"
        },
        "rebate": {
            "pos": [228, 240],
            "pic": "9(11)V9(2)"
        },
        "discount": {
            "pos": [241, 253],
            "pic": "9(11)V9(2)"
        },
        "receivedvalue": {
            "pos": [254, 266],
            "pic": "9(11)V9(2)"
        },
        "dayinterest": {
            "pos": [267, 279],
            "pic": "9(11)V9(2)"
        },
        "otherreceipt": {
            "pos": [280, 292],
            "pic": "9(11)V9(2)"
        },
        "abatmentnotuse": {
            "pos": [293, 305],
            "pic": "9(11)V9(2)"
        },
        "releasevalue": {
            "pos": [306, 318],
            "pic": "9(11)V9(2)"
        },
        "debitorcredit": {
            "pos": [319, 319],
            "pic": "9(01)"
        },
        "valueindicator": {
            "pos": [320, 320],
            "pic": "9(02)"
        },
        "valueadjust": {
            "pos": [321, 332],
            "pic": "9(11)V9(2)"
        },
        "s5": {
            "pos": [333, 333],
            "pic": "X(01)"
        },
        "s6": {
            "pos": [334, 342],
            "pic": "9(09)"
        },
        "z1": {
            "pos": [343, 349],
            "pic": "9(07)"
        },
        "z2": {
            "pos": [350, 358],
            "pic": "9(09)"
        },
        "z3": {
            "pos": [359, 365],
            "pic": "9(07)"
        },
        "z4": {
            "pos": [366, 374],
            "pic": "9(09)"
        },
        "z5": {
            "pos": [375, 381],
            "pic": "9(07)"
        },
        "z6": {
            "pos": [382, 390],
            "pic": "9(09)"
        },
        "indicatorautopartial": {
            "pos": [391, 391],
            "pic": "9(01)"
        },
        "s7": {
            "pos": [392, 392],
            "pic": "X(01)"
        },
        "channel": {
            "pos": [393, 394],
            "pic": "9(02)"
        },
        "seq": {
            "pos": [395, 400],
            "pic": "9(06)"
        }
    },
    "trailer": {
        "regtype": {
            "pos": [1, 1],
            "pic": "9(01)"
        },
        "n2": {
            "pos": [2, 2],
            "pic": "9(01)",
            "def": "2"
        },
        "n01": {
            "pos": [3, 4],
            "pic": "9(02)",
            "def": "01"
        },
        "n001": {
            "pos": [5, 7],
            "pic": "9(03)",
            "def": "001"
        },
        "s1": {
            "pos": [8, 17],
            "pic": "X(10)"
        },
        "quantsimple": {
            "pos": [18, 25],
            "pic": "9(08)"
        },
        "valuesimple": {
            "pos": [26, 39],
            "pic": "9(12)V9(2)"
        },
        "numbersimple": {
            "pos": [40, 47],
            "pic": "9(08)"
        },
        "s1": {
            "pos": [48, 57],
            "pic": "X(10)"
        },
        "quantlink": {
            "pos": [58, 65],
            "pic": "9(08)"
        },
        "valuelink": {
            "pos": [66, 79],
            "pic": "9(12)V9(2)"
        },
        "numberlink": {
            "pos": [80, 87],
            "pic": "9(08)"
        },
        "s2": {
            "pos": [88, 97],
            "pic": "X(10)"
        },
        "quantescrow": {
            "pos": [98, 105],
            "pic": "9(08)"
        },
        "valueescrow": {
            "pos": [106, 119],
            "pic": "9(12)V9(2)"
        },
        "numberescrow": {
            "pos": [120, 127],
            "pic": "9(08)"
        },
        "s3": {
            "pos": [128, 137],
            "pic": "X(10)"
        },
        "quantdiscount": {
            "pos": [138, 145],
            "pic": "9(08)"
        },
        "valuediscount": {
            "pos": [146, 159],
            "pic": "9(12)V9(2)"
        },
        "numberdiscount": {
            "pos": [160, 167],
            "pic": "9(08)"
        },
        "s4": {
            "pos": [168, 217],
            "pic": "X(50)"
        },
        "quantvendor": {
            "pos": [218, 225],
            "pic": "9(08)"
        },
        "valuevendor": {
            "pos": [226, 239],
            "pic": "9(12)V9(2)"
        },
        "numbervendor": {
            "pos": [240, 247],
            "pic": "9(08)"
        },
        "s5": {
            "pos": [248, 394],
            "pic": "X(147)"
        },
        "seq": {
            "pos": [395, 400],
            "pic": "9(06)"
        }
    }
}


